Metadata-Version: 2.4
Name: django-silent-mammoth-whistle
Version: 2.5
Summary: A super-simple user analytics tool that tracks user behaviour based on web requests to your Django app.
Author-email: Ben Michie <benopotamus@tinku.net>
License: BSD-2-Clause
Project-URL: Homepage, https://github.com/benopotamus/django-silent-mammoth-whistle
Project-URL: Documentation, https://github.com/benopotamus/django-silent-mammoth-whistle/blob/main/README.rst
Project-URL: Repository, https://github.com/benopotamus/django-silent-mammoth-whistle
Project-URL: Bug Tracker, https://github.com/benopotamus/django-silent-mammoth-whistle/issues
Project-URL: Changelog, https://github.com/benopotamus/django-silent-mammoth-whistle/blob/main/CHANGELOG.rst
Keywords: django,analytics,user,tracking
Classifier: Environment :: Web Environment
Classifier: Framework :: Django
Classifier: Framework :: Django :: 4.2
Classifier: Framework :: Django :: 5.0
Classifier: Framework :: Django :: 5.1
Classifier: Intended Audience :: Developers
Classifier: License :: OSI Approved :: BSD License
Classifier: Operating System :: OS Independent
Classifier: Programming Language :: Python
Classifier: Programming Language :: Python :: 3
Classifier: Programming Language :: Python :: 3.10
Classifier: Programming Language :: Python :: 3.11
Classifier: Programming Language :: Python :: 3.12
Classifier: Programming Language :: Python :: 3.13
Classifier: Topic :: Internet :: WWW/HTTP
Classifier: Topic :: Internet :: WWW/HTTP :: Dynamic Content
Requires-Python: >=3.10
License-File: LICENSE
Requires-Dist: django>=4.2
Requires-Dist: user-agents>=2.2.0
Dynamic: license-file
